README.txt
setup.cfg
setup.py
Products/__init__.py
Products.FileExchange.egg-info/PKG-INFO
Products.FileExchange.egg-info/SOURCES.txt
Products.FileExchange.egg-info/dependency_links.txt
Products.FileExchange.egg-info/entry_points.txt
Products.FileExchange.egg-info/namespace_packages.txt
Products.FileExchange.egg-info/not-zip-safe
Products.FileExchange.egg-info/requires.txt
Products.FileExchange.egg-info/top_level.txt
Products/FileExchange/CHANGES.txt
Products/FileExchange/__init__.py
Products/FileExchange/config.py
Products/FileExchange/configure.zcml
Products/FileExchange/interfaces.py
Products/FileExchange/setuphandlers.py
Products/FileExchange/utils.py
Products/FileExchange/version.txt
Products/FileExchange/browser/__init__.py
Products/FileExchange/browser/configure.zcml
Products/FileExchange/browser/fileexchange.css
Products/FileExchange/browser/views.py
Products/FileExchange/browser/images/add_file_icon.gif
Products/FileExchange/browser/images/add_file_icon_big.gif
Products/FileExchange/browser/images/delete_file_icon.gif
Products/FileExchange/browser/images/edit_file_icon.gif
Products/FileExchange/browser/images/fileexchangecontainer_icon.gif
Products/FileExchange/browser/images/received_files_icon.gif
Products/FileExchange/browser/images/user_files_icon.gif
Products/FileExchange/browser/templates/fileexchangecontainer.pt
Products/FileExchange/content/__init__.py
Products/FileExchange/content/fileexchangecontainer.py
Products/FileExchange/content/fileexchangefile.py
Products/FileExchange/i18n/FileExchange-de-plone.po
Products/FileExchange/i18n/FileExchange-fr-plone.po
Products/FileExchange/i18n/FileExchange-it-plone.po
Products/FileExchange/profiles/default/actions.xml
Products/FileExchange/profiles/default/factorytool.xml
Products/FileExchange/profiles/default/fileexchange_various.txt
Products/FileExchange/profiles/default/import_steps.xml
Products/FileExchange/profiles/default/metadata.xml
Products/FileExchange/profiles/default/propertiestool.xml
Products/FileExchange/profiles/default/rolemap.xml
Products/FileExchange/profiles/default/types.xml
Products/FileExchange/profiles/default/workflows.xml
Products/FileExchange/profiles/default/types/FileExchange_Container.xml
Products/FileExchange/profiles/default/types/FileExchange_File.xml
Products/FileExchange/profiles/default/workflows/fileexchange_workflow/definition.xml
