Metadata-Version: 1.0
Name: Products.FileExchange
Version: 2.0b2
Summary: Provides a userfriendly view to exchange files between users
Home-page: http://plone.org/products/fileexchange
Author: Raptus AG
Author-email: dev@raptus.com
License: GPL
Keywords: Plone File Exchange Upload
Platform: UNKNOWN
Classifier: Programming Language :: Python
Classifier: Topic :: Software Development :: Libraries :: Python Modules
